locality/__init__.py
locality/admin.py
locality/forms.py
locality/managers.py
locality/models.py
locality/urls.py
locality/views.py
locality/fixtures/locality.json
locality/migrations/0001_initial.py
locality/migrations/__init__.py
django_locality_two-3.1.dist-info/AUTHORS
django_locality_two-3.1.dist-info/LICENSE
django_locality_two-3.1.dist-info/METADATA
django_locality_two-3.1.dist-info/WHEEL
django_locality_two-3.1.dist-info/top_level.txt
django_locality_two-3.1.dist-info/RECORD
